clicra/__init__.py
clicra/clicra.py
clicra-0.2.4.dist-info/METADATA
clicra-0.2.4.dist-info/WHEEL
clicra-0.2.4.dist-info/entry_points.txt
clicra-0.2.4.dist-info/top_level.txt
clicra-0.2.4.dist-info/RECORD
