Metadata-Version: 2.1
Name: clicra
Version: 0.2.4
Summary: A LLM command-line crafter
Author-email: Toshihiro Kamiya <kamiya@mbj.nifty.com>
License: MIT LICENSE
Project-URL: Souce, https://github.com/tos-kamiya/clicra
Keywords: cli-tool,LLM
Classifier: Development Status :: 3 - Alpha
Classifier: Intended Audience :: Developers
Classifier: License :: OSI Approved :: MIT License
Classifier: Programming Language :: Python :: 3.8
Classifier: Operating System :: POSIX :: Linux
Requires-Python: >=3.10
Requires-Dist: ollama >=0.1.9
Requires-Dist: pyperclip >=1.8.2
Requires-Dist: termcolor >=2.4.0
Requires-Dist: setuptools >=61
